{
  "$schema": "https://dl.viam.dev/module.schema.json",
  "module_id": "wootter:dht22",
  "visibility": "public",
  "url": "https://github.com/Wootter/viam-dht22-module",
  "description": "A Viam module for the DHT22 temperature and humidity sensor on Raspberry Pi",
  "models": [
    {
      "api": "rdk:component:sensor",
      "model": "wootter:sensor:dht22"
    }
  ],
  "entrypoint": "run.sh",
  "build": {
    "build": "tar -czf module.tar.gz run.sh requirements.txt src",
    "path": "module.tar.gz",
    "arch": ["linux/arm64", "linux/amd64"]
  }
}